osia/__init__.py
osia/cli.py
osia/config/__init__.py
osia/config/config.py
osia/installer/__init__.py
osia/installer/clouds/__init__.py
osia/installer/clouds/aws.py
osia/installer/clouds/base.py
osia/installer/clouds/openstack.py
osia/installer/dns/__init__.py
osia/installer/dns/base.py
osia/installer/dns/nsupdate.py
osia/installer/dns/route53.py
osia/installer/downloader/__init__.py
osia/installer/downloader/image.py
osia/installer/downloader/install.py
osia/installer/downloader/utils.py
osia/installer/executor.py
osia/installer/storage.py
osia/installer/templates/__init__.py
osia/installer/templates/aws.jinja2
osia/installer/templates/install-config-base.yaml.jinja2
osia/installer/templates/openstack.jinja2
osia/installer/webhooks/__init__.py
osia/installer/webhooks/gchat.py
osia/installer/webhooks/webhook.py
osia-0.2.0a16.dist-info/AUTHORS
osia-0.2.0a16.dist-info/LICENSE
osia-0.2.0a16.dist-info/METADATA
osia-0.2.0a16.dist-info/WHEEL
osia-0.2.0a16.dist-info/entry_points.txt
osia-0.2.0a16.dist-info/RECORD
