Metadata-Version: 2.3
Name: osia
Version: 0.2.0a16
Summary: OpenShift infra automation
License: Apache-2.0
Keywords: OpenShift,OpenStack,AWS,automation
Author: Miroslav Jaros
Author-email: mirek@mijaros.cz
Maintainer: Matej Dujava
Maintainer-email: mdujava@redhat.com
Requires-Python: >=3.10,<4.0
Classifier: Development Status :: 3 - Alpha
Classifier: Intended Audience :: Developers
Classifier: License :: OSI Approved :: Apache Software License
Classifier: Programming Language :: Python :: 3
Classifier: Programming Language :: Python :: 3.10
Classifier: Programming Language :: Python :: 3.11
Classifier: Programming Language :: Python :: 3.12
Classifier: Programming Language :: Python :: 3.13
Classifier: Topic :: Software Development :: Build Tools
Requires-Dist: beautifulsoup4
Requires-Dist: boto3
Requires-Dist: coloredlogs
Requires-Dist: distro
Requires-Dist: dynaconf[yaml]
Requires-Dist: gitpython
Requires-Dist: jinja2
Requires-Dist: openstacksdk
Requires-Dist: semantic-version (>=2.10.0,<3.0.0)
Requires-Dist: urllib3
